[
  {
    "word": "Quand",
    "start": 0.68,
    "end": 0.84
  },
  {
    "word": "je",
    "start": 0.84,
    "end": 0.96
  },
  {
    "word": "vois",
    "start": 0.96,
    "end": 1.12
  },
  {
    "word": "un",
    "start": 1.12,
    "end": 1.2
  },
  {
    "word": "sans-abri",
    "start": 1.2,
    "end": 1.64
  },
  {
    "word": "dans",
    "start": 1.64,
    "end": 1.72
  },
  {
    "word": "la",
    "start": 1.72,
    "end": 1.92
  },
  {
    "word": "rue,",
    "start": 1.92,
    "end": 2.32
  },
  {
    "word": "je",
    "start": 2.32,
    "end": 2.52
  },
  {
    "word": "ne",
    "start": 2.52,
    "end": 2.6
  },
  {
    "word": "peux",
    "start": 2.6,
    "end": 2.72
  },
  {
    "word": "pas",
    "start": 2.72,
    "end": 2.88
  },
  {
    "word": "ne",
    "start": 2.88,
    "end": 3
  },
  {
    "word": "pas",
    "start": 3,
    "end": 3.16
  },
  {
    "word": "m'arrêter",
    "start": 3.16,
    "end": 3.6
  },
  {
    "word": "sans",
    "start": 3.6,
    "end": 3.72
  },
  {
    "word": "lui",
    "start": 3.72,
    "end": 3.84
  },
  {
    "word": "acheter",
    "start": 3.84,
    "end": 4.12
  },
  {
    "word": "à",
    "start": 4.12,
    "end": 4.2
  },
  {
    "word": "manger",
    "start": 4.2,
    "end": 4.64
  },
  {
    "word": "en",
    "start": 4.64,
    "end": 4.84
  },
  {
    "word": "ayant",
    "start": 4.84,
    "end": 5
  },
  {
    "word": "les",
    "start": 5,
    "end": 5.12
  },
  {
    "word": "larmes",
    "start": 5.12,
    "end": 5.36
  },
  {
    "word": "aux",
    "start": 5.36,
    "end": 5.4
  },
  {
    "word": "yeux.",
    "start": 5.4,
    "end": 5.76
  }
]